psyflow/BlockUnit.py
psyflow/LLM.py
psyflow/StimBank.py
psyflow/StimUnit.py
psyflow/SubInfo.py
psyflow/TaskSettings.py
psyflow/TriggerSender.py
psyflow/__init__.py
psyflow/_version.py
psyflow/cli.py
psyflow/utils.py
psyflow/templates/cookiecutter-psyflow/cookiecutter.json
psyflow/templates/cookiecutter-psyflow/{{cookiecutter.project_name}}/README.md
psyflow/templates/cookiecutter-psyflow/{{cookiecutter.project_name}}/main.py
psyflow/templates/cookiecutter-psyflow/{{cookiecutter.project_name}}/src/__init__.py
psyflow/templates/cookiecutter-psyflow/{{cookiecutter.project_name}}/src/run_trial.py
psyflow/templates/cookiecutter-psyflow/{{cookiecutter.project_name}}/src/utils.py
psyflow-0.1.2.dist-info/licenses/LICENSE
psyflow-0.1.2.dist-info/METADATA
psyflow-0.1.2.dist-info/WHEEL
psyflow-0.1.2.dist-info/entry_points.txt
psyflow-0.1.2.dist-info/top_level.txt
psyflow-0.1.2.dist-info/RECORD
