Metadata-Version: 2.4
Name: psyflow
Version: 0.1.2
Summary: A utility package for building modular PsychoPy experiments.
Author: Zhipeng Cao
Author-email: Zhipeng Cao <zhipeng30@foxmail.com>
License-File: LICENSE
Requires-Dist: psychopy
Requires-Dist: numpy
Requires-Dist: pandas
Requires-Dist: click
Requires-Dist: cookiecutter
Requires-Dist: pyyaml
Requires-Dist: pyserial
Requires-Dist: edge-tts
Requires-Dist: requests
Requires-Dist: tiktoken
Requires-Dist: openai
Requires-Dist: google-generativeai
Dynamic: author
Dynamic: license-file
